tasktracker_ehdlg/__init__.py
tasktracker_ehdlg/__main__.py
tasktracker_ehdlg/actions.py
tasktracker_ehdlg/data_service.py
tasktracker_ehdlg/parser.py
tasktracker_ehdlg-1.0.1.dist-info/METADATA
tasktracker_ehdlg-1.0.1.dist-info/WHEEL
tasktracker_ehdlg-1.0.1.dist-info/entry_points.txt
tasktracker_ehdlg-1.0.1.dist-info/top_level.txt
tasktracker_ehdlg-1.0.1.dist-info/RECORD
