Metadata-Version: 2.1
Name: tasktracker-ehdlg
Version: 1.0.1
Summary: Simple task tracker CLI program to manage your tasks
Author: Enrique Hidalgo
Project-URL: Homepage, https://github.com/ehdlg/task-tracker
Keywords: tasks,cli
Requires-Python: >=3.9
Requires-Dist: tabulate
Requires-Dist: colorama
